MANIFEST.in
setup.py
cmsplugin_socialschools/__init__.py
cmsplugin_socialschools/cms_plugins.py
cmsplugin_socialschools/models.py
cmsplugin_socialschools/tests.py
cmsplugin_socialschools/views.py
cmsplugin_socialschools.egg-info/PKG-INFO
cmsplugin_socialschools.egg-info/SOURCES.txt
cmsplugin_socialschools.egg-info/dependency_links.txt
cmsplugin_socialschools.egg-info/not-zip-safe
cmsplugin_socialschools.egg-info/top_level.txt
cmsplugin_socialschools/locale/en/LC_MESSAGES/django.mo
cmsplugin_socialschools/locale/en/LC_MESSAGES/django.po
cmsplugin_socialschools/locale/nl/LC_MESSAGES/django.mo
cmsplugin_socialschools/locale/nl/LC_MESSAGES/django.po
cmsplugin_socialschools/migrations/0001_initial.py
cmsplugin_socialschools/migrations/0002_auto_20160718_1114.py
cmsplugin_socialschools/migrations/__init__.py
cmsplugin_socialschools/static/cmsplugin_socialschools/js/socialschools.js
cmsplugin_socialschools/static/cmsplugin_socialschools/js/socialschools_cmsplugin.js
cmsplugin_socialschools/static/cmsplugin_socialschools/js/lib/bootstrap-image-gallery.js
cmsplugin_socialschools/static/cmsplugin_socialschools/js/lib/bootstrap.min.js
cmsplugin_socialschools/static/cmsplugin_socialschools/js/lib/load-image.min.js
cmsplugin_socialschools/static/cmsplugin_socialschools/js/lib/moment+langs.min.js
cmsplugin_socialschools/static/cmsplugin_socialschools/js/lib/underscore-min.js
cmsplugin_socialschools/templates/cms_plugins/socialschools/comment.html
cmsplugin_socialschools/templates/cms_plugins/socialschools/document.html
cmsplugin_socialschools/templates/cms_plugins/socialschools/event.html
cmsplugin_socialschools/templates/cms_plugins/socialschools/news.html
cmsplugin_socialschools/templates/cms_plugins/socialschools/newsphoto.html
cmsplugin_socialschools/templates/cms_plugins/socialschools/newsthumb.html
cmsplugin_socialschools/templates/cms_plugins/socialschools/newsthumbwithoutevent.html
cmsplugin_socialschools/templates/cms_plugins/socialschools/photo.html
cmsplugin_socialschools/templates/cms_plugins/socialschools/post.html
cmsplugin_socialschools/templates/cms_plugins/socialschools/postwithoutevent.html
cmsplugin_socialschools/templates/cms_plugins/socialschools/pubphoto.html
