Metadata-Version: 1.0
Name: cmsplugin-socialschools
Version: 1.3.3
Summary: SocialSchools plugin for django-cms
Home-page: UNKNOWN
Author: Pratik Vyas
Author-email: pratik.vyas@changer.nl
License: UNKNOWN
Platform: UNKNOWN
